nlpbasic/__init__.py
nlpbasic/main.py
nlpbasic-0.2.dist-info/METADATA
nlpbasic-0.2.dist-info/WHEEL
nlpbasic-0.2.dist-info/top_level.txt
nlpbasic-0.2.dist-info/RECORD
