Metadata-Version: 2.1
Name: nlpbasic
Version: 0.2
